mekadb/mekadb.py
mekadb/mekadb_client_pb2.py
mekadb/mekadb_client_pb2.pyi
mekadb/mekadb_client_pb2_grpc.py
mekadb-0.1.0.dist-info/METADATA
mekadb-0.1.0.dist-info/WHEEL
mekadb-0.1.0.dist-info/licenses/LICENSE
mekadb-0.1.0.dist-info/RECORD
