Metadata-Version: 2.1
Name: mekadb
Version: 0.1.0
Summary: Hypi MekaDB database client
Project-URL: Homepage, https://hypi.ai
Project-URL: Issues, https://hypi.ai
Author-email: Hypi <oss@hypi.io>
License-File: LICENSE
Classifier: License :: OSI Approved :: Apache Software License
Classifier: Operating System :: OS Independent
Classifier: Programming Language :: Python :: 3
Classifier: Topic :: Database
Classifier: Topic :: Database :: Front-Ends
Requires-Python: >=3.7
